{
  "id": "math-subtraction",
  "title": "ひきざん",
  "emoji": "➖",
  "type": "math",
  "totalQuestions": 10,
  "choiceCount": 4,
  "reward": { "perCorrect": 2 },
  "questItems": [
    { "id": "rabbit", "emoji": "🐰", "name": "うさぎ" },
    { "id": "dog", "emoji": "🐶", "name": "いぬ" },
    { "id": "cat", "emoji": "🐱", "name": "ねこ" },
    { "id": "bear", "emoji": "🐻", "name": "くま" },
    { "id": "panda", "emoji": "🐼", "name": "ぱんだ" },
    { "id": "lion", "emoji": "🦁", "name": "らいおん" },
    { "id": "monkey", "emoji": "🐵", "name": "さる" },
    { "id": "frog", "emoji": "🐸", "name": "かえる" }
  ],
  "levels": [
    {
      "name": "レベル1: 1けた-1けた",
      "desc": "5-2=3",
      "kind": "diff",
      "num1Range": [5, 9],
      "num2LtNum1": true,
      "choiceRange": 10,
      "template": "おべんとうが {num1}こ あったよ。{num2}こ とどけたら のこりは なんこ？"
    },
    {
      "name": "レベル2: 2けた-1けた",
      "desc": "15-3=12",
      "kind": "diff",
      "num1Range": [10, 99],
      "num2Range": [1, 9],
      "choiceRange": 10,
      "template": "おべんとうが {num1}こ あったよ。{num2}こ とどけたら のこりは なんこ？"
    },
    {
      "name": "レベル3: 2けた-2けた",
      "desc": "25-13=12",
      "kind": "diff",
      "num1Range": [10, 99],
      "num2LtNum1": true,
      "choiceRange": 10,
      "template": "おべんとうが {num1}こ あったよ。{num2}こ とどけたら のこりは なんこ？"
    }
  ]
}
